[
    {
        "source_file": "mulligan_studies.json",
        "title": "PHYSIOTHERAPY IN CERVICOGENIC HEADACHE FROM THE PERSPECTIVE OF CERTIFIED MULLIGAN CONCEPT® PRACTITIONERS - A DELPHI STUDY",
        "publication_year": 2023,
        "authors": [
            "Yasemin Özel Aslıyüce",
            "Özlem Ülger"
        ]
    },
    {
        "source_file": "mulligan_studies.json",
        "title": "Effectiveness of Mulligan Mobilization with Conventional Physiotherapy In Knee Osteoarthritis: - A Case Series",
        "publication_year": 2015,
        "authors": [
            "Vrushali S. Jadhav",
            "Deepak Anap"
        ]
    },
    {
        "source_file": "mulligan_studies.json",
        "title": "To compare effectiveness of mulligan bent leg raise versus myofacial release in physiotherapy students with hamstring tightness",
        "publication_year": 2017,
        "authors": [
            "Mohammed Zaid Tai",
            "Megha Bandawde",
            "Tushar Palekar J.",
            "Diksha Gondkar"
        ]
    },
    {
        "source_file": "mulligan_studies.json",
        "title": "Effectiveness Of Mulligan Mobilization with Movement Versus Conventional Physiotherapy Exercises in Type 2 Diabetic Individuals with Frozen Shoulder",
        "publication_year": 2024,
        "authors": [
            "S. Prakash",
            "Rakesh Kumar Singh",
            "Shailendra Mehta"
        ]
    },
    {
        "source_file": "mulligan_studies.json",
        "title": "Physiotherapeutic Intervention Techniques for Knee Osteoarthritis: A Systematic Review",
        "publication_year": 2024,
        "authors": [
            "Kamya J Somaiya",
            "Subrat Samal",
            "Manali A Boob"
        ]
    },
    {
        "source_file": "mulligan_studies.json",
        "title": "A Review on Treatment Approaches for Chronic Low Back Pain via Mulligans Movement With Mobilization and Physical Therapy",
        "publication_year": 2022,
        "authors": [
            "Neha Chitale",
            "Deepali S Patil",
            "Pratik Phansopkar",
            "Aditi Joshi"
        ]
    },
    {
        "source_file": "mulligan_studies.json",
        "title": "Comparison of subtalar mobilization with conventional physiotherapy treatment for the management of planter fasciitis",
        "publication_year": 2021,
        "authors": [
            "Muhammad Kashif",
            "Abdulaziz Aoudh Albalwi",
            "Ahmed Abdullah Alharbi",
            "Humaira Iram",
            "Nosheen Manzoor"
        ]
    },
    {
        "source_file": "mulligan_studies.json",
        "title": "Effect of Mulligan Bent Leg Raise versus Neural Mobilization on Hamstring Tightness in College Students",
        "publication_year": 2017,
        "authors": [
            "Shrinivas Vinayakrao Shinde"
        ]
    },
    {
        "source_file": "mulligan_studies.json",
        "title": "Joint Mobilization: Theory and evidence review",
        "publication_year": 2020,
        "authors": [
            "Lucky Anggiat",
            "Andrei Joseph Altavas",
            "Weeke Budhyanti",
            "Weeke Budhyanti",
            "Physical Therapy Advancement Seminars, Florida, United States of America"
        ]
    },
    {
        "source_file": "mulligan_studies.json",
        "title": "Comparison of Effectiveness of Mulligan ‘MWM’ Technique Versus Kaltenborn Mobilization Technique on Pain and End Range of Motion in Patients with Adhesive Capsulitis of Shoulder Joint : A Randomized Controlled Trial",
        "publication_year": 2019,
        "authors": [
            "Sumit Ragav",
            "Anshika Singh"
        ]
    },
    {
        "source_file": "mulligan_studies.json",
        "title": "Effectiveness of Mulligan Mobilization Technique Versus Cyriax Technique for Lateral Epicondylitis: A Pilot Study",
        "publication_year": 2024,
        "authors": [
            "Dhivya Shree Y",
            "Jagatheesan Alagaesan",
            "Jeslin Godwin Nirmala"
        ]
    },
    {
        "source_file": "mulligan_studies.json",
        "title": "Guidelines for Management of Ischaemic Stroke and Transient Ischaemic Attack 2008",
        "publication_year": 2008,
        "authors": [
            "Peter A. Ringleb",
            "Marie Germaine Bousser"
        ]
    },
    {
        "source_file": "mulligan_studies.json",
        "title": "Comparing the effectiveness of mulligan mobilization versus cyriax approach in the management of patients with subacute lateral epicondylitis",
        "publication_year": 2020,
        "authors": [
            "Aqeel Ahmed",
            "Muhammad Ibrar",
            "Aatik Arsh",
            "Sonia Wali",
            "Shoukat Hayat",
            "Summar Abass"
        ]
    },
    {
        "source_file": "mulligan_studies.json",
        "title": "EFFECTS OF MULLIGAN AND CYRIAX APPROACH IN PATIENTS WITH SUBACUTE LATERAL EPICONDYLITIS",
        "publication_year": 2019,
        "authors": [
            "Sammar Abbas",
            "Rabbiya Riaz",
            "Aqeel Ahmed Khan",
            "Anam Javed",
            "Shahid Masood Raza"
        ]
    },
    {
        "source_file": "mulligan_studies.json",
        "title": "Short-term Effect of Mulligan SNAGs on Pain Intensity, Cervical Range of Motion and Craniovertebral Angle in Patients with Non Specific Neck Pain: A Quasi-experimental Study",
        "publication_year": 2022,
        "authors": [
            "Karthik Vijayan",
            "Arulpragassame Sivaraman",
            "Parkavi Kumaresan",
            "Jayalakshmi Palani"
        ]
    },
    {
        "source_file": "mulligan_studies.json",
        "title": "Comparative Effects of Mulligan’s Two Leg Rotation Technique and Muscle Energy Technique on Hamstring Flexibility",
        "publication_year": 2022,
        "authors": [
            "Maryam Razzaq",
            "Zahid Mehmood Bhatti",
            "Umber Nawaz",
            "Hafiza Muriam Ghani",
            "Zaib-Un- Nisa",
            "Maryam Hina"
        ]
    },
    {
        "source_file": "mulligan_studies.json",
        "title": "PEMBERIAN TEKNIK MULLIGAN DAN SOFT TISSUE MOBILIZATION LEBIH BAIK DARIPADA HANYA SOFT TISSUE MOBILIZATION DALAM MENINGKATKAN LINGKUP GERAK SENDI EKSTENSI, ROTASI, LATERAL FLEKSI CERVICAL PADA MECHANICAL NECK PAIN",
        "publication_year": 2013,
        "authors": [
            "sudaryanto",
            "Dewa Putu Sutjana",
            "Muhammad Irfan"
        ]
    },
    {
        "source_file": "mulligan_studies.json",
        "title": "Benefits and harms of spinal manipulative therapy for the treatment of chronic low back pain: systematic review and meta-analysis of randomised controlled trials",
        "publication_year": 2019,
        "authors": [
            "Sidney M. Rubinstein",
            "Annemarie de Zoete",
            "Marienke van Middelkoop",
            "Willem JJ Assendelft",
            "Michiel R. de Boer",
            "Maurits W. van Tulder"
        ]
    },
    {
        "source_file": "mulligan_studies.json",
        "title": "The effectiveness of headache treatment using manual therapy techniques according to the Brian Mulligan concept",
        "publication_year": 2021,
        "authors": [
            "Piotr Szomiński",
            "Dominika Bacz"
        ]
    },
    {
        "source_file": "mulligan_studies.json",
        "title": "Comparison between Mulligan Sustained natural apophyseal glides (snags) VS McKenzie exercises in Chronic Mechanical Low back pain",
        "publication_year": 2022,
        "authors": [
            "Sumbal Salik",
            "Shaista Rani",
            "Rehana Hayat",
            "Sana Manzoor",
            "Amber Usama Malik",
            "Sania Maqbool"
        ]
    },
    {
        "source_file": "mulligan_studies.json",
        "title": "Efficacy of Mulligan on electromyography activation of cervical muscles in mechanical neck pain: randomised experimental trial",
        "publication_year": 2023,
        "authors": [
            "Alshaymaa Shaaban Abd El-Azeim",
            "Mariam Omran Grase"
        ]
    },
    {
        "source_file": "mulligan_studies.json",
        "title": "Effectiveness of Maitland Mobilization Technique in Comparison with Mulligan Mobilization Technique in Management of Frozen Shoulder",
        "publication_year": 2023,
        "authors": [
            "Mamoona Anwar",
            "Muhammad Waqas Mughal",
            "Nabira Izhar",
            "Maryam Rasheed"
        ]
    },
    {
        "source_file": "mulligan_studies.json",
        "title": "Physiotherapy Efficacy of Mulligan Technique in Subacromial Conflict: Literature Review",
        "publication_year": 2022,
        "authors": [
            "Selda Veizaj",
            "Ariola Mena",
            "Jonida Drizaj"
        ]
    },
    {
        "source_file": "mulligan_studies.json",
        "title": "Comparison of Maitland Mobilization and Mulligan Mobilization with Movement in Knee Osteoarthritis Patients",
        "publication_year": 2021,
        "authors": [
            "Zeeshan Mehmood",
            "Naveed Anwar",
            "Sana Tauqeer",
            "Maryam Shabbir",
            "Kehkshan Khalid",
            "Sajid Mehmood"
        ]
    },
    {
        "source_file": "mulligan_studies.json",
        "title": "Comparison of Maitland Mobilization and Mulligan Mobilization with movement on pain and hand function in patients having post Colle’s Fracture Stiffness",
        "publication_year": 2022,
        "authors": [
            "Maham Javaid",
            "Sahreen Anwar",
            "Hafiz Muhammad Uzair Asghar",
            "Wajida Perveen",
            "Junaid Akhtar",
            "Zeeshan Mustafa",
            "Fatima Amin"
        ]
    },
    {
        "source_file": "mdt_studies.json",
        "title": "Randomized trial of two physiotherapy interventions for primary care neck and back pain patients: 'McKenzie' vs brief physiotherapy pain management",
        "publication_year": 2006,
        "authors": [
            "J Klaber Moffett",
            "David A. Jackson",
            "Eric Gardiner",
            "David Torgerson",
            "Simon Coulton",
            "Sharyn Eaton",
            "M. P. Mooney",
            "Carolyn Pickering",
            "A. J. Green",
            "Liz Walker",
            "Stephen May",
            "Steve Young"
        ]
    },
    {
        "source_file": "mdt_studies.json",
        "title": "The conservative treatment of low back pain : a study of McKenzie physiotherapy and slow release ketoprofen",
        "publication_year": 1991,
        "authors": [
            "Andrew Roberts"
        ]
    },
    {
        "source_file": "mdt_studies.json",
        "title": "Randomized trial of two physiotherapy interventions for primary care back and neck pain patients: cost effectiveness analysis",
        "publication_year": 2007,
        "authors": [
            "Andrea Manca",
            "Jo C Dumville",
            "David Torgerson",
            "J. A. Klaber Moffett",
            "M. P. Mooney",
            "David A. Jackson",
            "Sharyn Eaton"
        ]
    },
    {
        "source_file": "mdt_studies.json",
        "title": "PRISMA 2020 explanation and elaboration: updated guidance and exemplars for reporting systematic reviews",
        "publication_year": 2021,
        "authors": [
            "Matthew J. Page",
            "David Moher",
            "Patrick M. Bossuyt",
            "Isabelle Boutron",
            "Tammy Hoffmann",
            "Cynthia D. Mulrow",
            "Larissa Shamseer",
            "Jennifer Tetzlaff",
            "Elie A. Akl",
            "Sue Brennan",
            "Roger Chou",
            "Julie Glanville",
            "Jeremy Grimshaw",
            "Asbjørn Hróbjartsson",
            "Manoj M. Lalu",
            "Tianjing Li",
            "Elizabeth Loder",
            "Evan Mayo‐Wilson",
            "Steve McDonald",
            "Luke A. McGuinness",
            "Lesley Stewart",
            "James Thomas",
            "Andrea C. Tricco",
            "Vivian Welch",
            "Penny Whiting",
            "Joanne E. McKenzie"
        ]
    },
    {
        "source_file": "mdt_studies.json",
        "title": "Preferred reporting items for systematic review and meta-analysis protocols (PRISMA-P) 2015: elaboration and explanation",
        "publication_year": 2015,
        "authors": [
            "Larissa Shamseer",
            "David Moher",
            "Mike Clarke",
            "Davina Ghersi",
            "A. Liberati",
            "Mark Petticrew",
            "Paul Shekelle",
            "Lesley Stewart",
            "the PRISMA-P Group"
        ]
    },
    {
        "source_file": "mdt_studies.json",
        "title": "Health Care Providers' Attitudes and Beliefs Towards Common Low Back Pain: Factor Structure and Psychometric Properties of the HC-PAIRS",
        "publication_year": 2003,
        "authors": [
            "Ruud Houben",
            "Johan W.S. Vlaeyen",
            "Madelon L. Peters",
            "Raymond Ostelo",
            "Pieter Wolters",
            "Suzanne G. M. Stomp‐van den Berg"
        ]
    },
    {
        "source_file": "mdt_studies.json",
        "title": "Integrating evidence into practice: use of McKenzie-based treatment for mechanical low back pain",
        "publication_year": 2011,
        "authors": [
            "Saravana Kumar",
            "Dunsford",
            "Clarke"
        ]
    },
    {
        "source_file": "mdt_studies.json",
        "title": "Does Motor Control Exercise Restore Normal Morphology of Lumbar Multifidus Muscle in People with Low Back Pain? – A Systematic Review",
        "publication_year": 2021,
        "authors": [
            "Sabina M. Pinto",
            "Sweta B Boghra",
            "Luciana Macedo",
            "Yong‐Ping Zheng",
            "Marco Y.C. Pang",
            "Jason Pui Yin Cheung",
            "Jaro Karppinen",
            "Dino Samartzis",
            "Arnold Yu Lok Wong"
        ]
    },
    {
        "source_file": "mdt_studies.json",
        "title": "Chapter 4European guidelinesfor the management of chronicnonspecific low back pain",
        "publication_year": 2006,
        "authors": [
            "Olavi Airaksinen",
            "Jens Ivar Brox",
            "Christine Cedraschi",
            "J. Hildebrandt",
            "Jennifer Klaber-Moffett",
            "Francisco M. Kovacs",
            "Anne F. Mannion",
            "Sandra Marina dos Reis",
            "J. Bart Staal",
            "Holger Ursin",
            "Gustavo Zanoli",
            "On behalf of the COST B13 Working Group on Guidelines for Chronic Low Back Pain"
        ]
    },
    {
        "source_file": "mdt_studies.json",
        "title": "Lumbar disk prolapse: Response to mechanical physiotherapy in the absence of changes in magnetic resonance imaging. Report of 11 cases",
        "publication_year": 2008,
        "authors": [
            "Doris Broetz",
            "U. Hahn",
            "Evelin Maschke",
            "Wolfgang Wick",
            "W Kueker",
            "Michael Weller"
        ]
    },
    {
        "source_file": "mdt_studies.json",
        "title": "An official European Respiratory Society/American Thoracic Society technical standard: field walking tests in chronic respiratory disease",
        "publication_year": 2014,
        "authors": [
            "Anne E. Holland",
            "Martijn A. Spruit",
            "Thierry Troosters",
            "Milo A. Puhan",
            "Véronique Pepin",
            "Didier Saey",
            "Meredith C. McCormack",
            "Brian Carlin",
            "Frank C. Sciurba",
            "Fábio Pitta",
            "Jack Wanger",
            "Neil R. MacIntyre",
            "David A. Kaminsky",
            "Bruce H. Culver",
            "Susan M. Revill",
            "Nídia Aparecida Hernandes",
            "Vasileios Andrianopoulos",
            "Carlos Augusto Camillo",
            "Katy Mitchell",
            "Annemarie L. Lee",
            "Catherine J. Hill",
            "Sally Singh"
        ]
    },
    {
        "source_file": "mdt_studies.json",
        "title": "Joint Mobilization: Theory and evidence review",
        "publication_year": 2020,
        "authors": [
            "Lucky Anggiat",
            "Andrei Joseph Altavas",
            "Weeke Budhyanti",
            "Weeke Budhyanti",
            "Physical Therapy Advancement Seminars, Florida, United States of America"
        ]
    },
    {
        "source_file": "mdt_studies.json",
        "title": "Unveiling the Efficacy of Physiotherapy Strategies in Alleviating Low Back Pain: A Comprehensive Review of Interventions and Outcomes",
        "publication_year": 2024,
        "authors": [
            "Priya Tikhile",
            "Deepali S Patil"
        ]
    },
    {
        "source_file": "mdt_studies.json",
        "title": "Prevention and treatment of low back pain: evidence, challenges, and promising directions",
        "publication_year": 2018,
        "authors": [
            "Nadine E. Foster",
            "Johannes R. Anema",
            "Dan Cherkin",
            "Roger Chou",
            "Steven P. Cohen",
            "Douglas P. Gross",
            "Paulo H. Ferreira",
            "Julie M. Fritz",
            "Bart W. Koes",
            "Wilco C. Peul",
            "Judith A. Turner",
            "Christopher G. Maher",
            "Rachelle Buchbinder",
            "Jan Hartvigsen",
            "Dan Cherkin",
            "Nadine E. Foster",
            "Christopher G. Maher",
            "Martin Underwood",
            "Maurits W. van Tulder",
            "Johannes R. Anema",
            "Roger Chou",
            "Stephen P. Cohen",
            "Lucíola da Cunha Menezes Costa",
            "Peter Croft",
            "Manuela L. Ferreira",
            "Paulo H. Ferreira",
            "Julie M. Fritz",
            "Stéphane Genevay",
            "Douglas P. Gross",
            "Mark J. Hancock",
            "Damian Hoy",
            "Jaro Karppinen",
            "Bart W. Koes",
            "Alice Kongsted",
            "Quinette Louw",
            "Birgitta Öberg",
            "Wilco C. Peul",
            "Glenn Pransky",
            "Mark L. Schoene",
            "Joachim Sieper",
            "Rob Smeets",
            "Judith A. Turner",
            "Anthony D. Woolf"
        ]
    },
    {
        "source_file": "mdt_studies.json",
        "title": "Exercise therapy for treatment of non-specific low back pain",
        "publication_year": 2005,
        "authors": [
            "Jill A. Hayden",
            "Maurits W. van Tulder",
            "Antti Malmivaara",
            "Bart W. Koes"
        ]
    },
    {
        "source_file": "mdt_studies.json",
        "title": "A Comparison of Physical Therapy, Chiropractic Manipulation, and Provision of an Educational Booklet for the Treatment of Patients with Low Back Pain",
        "publication_year": 1998,
        "authors": [
            "Daniel C. Cherkin",
            "Richard A. Deyo",
            "Michele C. Battié",
            "Janet Street",
            "William E. Barlow"
        ]
    },
    {
        "source_file": "mdt_studies.json",
        "title": "National Clinical Guidelines for non-surgical treatment of patients with recent onset low back pain or lumbar radiculopathy",
        "publication_year": 2017,
        "authors": [
            "Mette Jensen Stochkendahl",
            "Per Kjær",
            "Jan Hartvigsen",
            "Alice Kongsted",
            "J. Aaboe",
            "Margrethe Andersen",
            "Mikkel Østerheden Andersen",
            "Gilles Fournier",
            "Betina Højgaard",
            "Martin Bach Jensen",
            "Lone Donbæk Jensen",
            "Ture Karbo",
            "Lilli Kirkeskov",
            "Mads Melbye",
            "Lone Morsel‐Carlsen",
            "Jan Nordsteen",
            "Þorvaldur Skúli Pálsson",
            "Zoreh Rasti",
            "Peter Frost Silbye",
            "Morten Zebitz Steiness",
            "Simon Tarp",
            "Morten Vaagholt"
        ]
    },
    {
        "source_file": "mdt_studies.json",
        "title": "Continuing education meetings and workshops: effects on professional practice and health care outcomes",
        "publication_year": 2009,
        "authors": [
            "Louise Forsetlund",
            "Arild Bjørndal",
            "Arash Rashidian",
            "Gro Jamtvedt",
            "Mary Ann O’Brien",
            "Fredric M. Wolf",
            "Dave Davis",
            "Jan Odgaard‐Jensen",
            "Andrew D Oxman"
        ]
    },
    {
        "source_file": "mdt_studies.json",
        "title": "The effect of physiotherapy and McKenzie exercises for patients with lumbar disc herniation.",
        "publication_year": 2016,
        "authors": [
            "Umbrasaitė, Živilė,"
        ]
    },
    {
        "source_file": "mdt_studies.json",
        "title": "Which specific modes of exercise training are most effective for treating low back pain? Network meta-analysis",
        "publication_year": 2019,
        "authors": [
            "Patrick J. Owen",
            "Clint T. Miller",
            "Niamh L Mundell",
            "Simone J.J.M. Verswijveren",
            "Scott D. Tagliaferri",
            "Helena Brisby",
            "Steven J. Bowe",
            "Daniel L. Belavý"
        ]
    },
    {
        "source_file": "mdt_studies.json",
        "title": "The effectiveness of the McKenzie method in treating lumbar discopathy",
        "publication_year": 2021,
        "authors": [
            "Arletta Hawrylak",
            "Aneta Demidaś",
            "Krystyna Chromik",
            "Adam Hawrylak"
        ]
    },
    {
        "source_file": "mdt_studies.json",
        "title": "2018 EULAR recommendations for physical activity in people with inflammatory arthritis and osteoarthritis",
        "publication_year": 2018,
        "authors": [
            "Anne-Kathrin Rausch Osthoff",
            "Karin Niedermann",
            "Jürgen Braun",
            "Jo Adams",
            "Nina Brodin",
            "Hanne Dagfinrud",
            "Mehmet Tuncay Duruöz",
            "Bente Appel Esbensen",
            "Klaus‐Peter Günther",
            "Emailie Hurkmans",
            "Carsten Bogh Juhl",
            "Norelee Kennedy",
            "Uta Kiltz",
            "Keegan Knittle",
            "Michael T. Nurmohamed",
            "Sandra Pais",
            "G Severijns",
            "Thijs Willem Swinnen",
            "I. Pitsillidou",
            "Louise Warburton",
            "Zhivko Yankov",
            "T. P. M. Vliet Vlieland"
        ]
    },
    {
        "source_file": "mdt_studies.json",
        "title": "A Review of Therapeutic Ultrasound: Biophysical Effects",
        "publication_year": 2001,
        "authors": [
            "Kerry Baker",
            "Valma J Robertson",
            "Francis Duck"
        ]
    },
    {
        "source_file": "mdt_studies.json",
        "title": "Efficacy of spinal manipulation and mobilization for low back pain and neck pain: a systematic review and best evidence synthesis",
        "publication_year": 2004,
        "authors": [
            "Gert Brønfort",
            "Mitchell Haas",
            "Roni Evans",
            "L.M. Bouter"
        ]
    },
    {
        "source_file": "mdt_studies.json",
        "title": "To Compare The Effect Of Core Stability Exercises And Muscle Energy Techniques On Low Back Pain Patients.",
        "publication_year": 2013,
        "authors": [
            "Apoorv Narain",
            "Jagmohan Singh",
            "Sabyasachi Bhowmik"
        ]
    }
]